A.sv
//-----------------------------------------------------------------------------------------------
//     Author: Edgar Alejandro Recancoj Pajarez
//     Proyect: Nibbler
//     Module: Acumulador
//     Date: 8/11/2018
//     Description of file: Acumulador for Nibbler
//--------------------------------------------------------------------------------------------

module A (input logic clk,
          input logic reset,
          input logic [3:0] ALU_Result,
          output logic [3:0] A_Result);

  always @ (posedge clk or posedge reset)
    begin//si esta en reset, se pone q en 0, si no, en el flanco positivo de clk se pasa d a q.
    if (reset)
      A_Result <= 4'b0;
  	else
      A_Result <= ALU_Result;
    end


endmodule

ALU.sv
//-----------------------------------------------------------------------------------------------
//     Author: Edgar Alejandro Recancoj Pajarez
//     Proyect: Nibbler
//     Module: ALU
//     Date: 8/11/2018
//     Description of file: ALU for Nibbler
//--------------------------------------------------------------------------------------------

module ALU #(parameter N = 4)
          (input  logic notCarryIn,
          input logic [2:0] S,
          input logic [N-1:0] A_Result,
          input logic [N-1:0] operand,
          input logic notOeALU,
          output logic notC,
          output logic notZ,
          output logic [N-1:0] ALU_Result);

  logic [3:0] modeSelect;
  assign modeSelect = {notCarryIn, S [2:0]};

  always @ (modeSelect)

    begin
      casez (modeSelect)
        4'b1000: begin ALU_Result = A_Result; notC = 1; notZ = 1; end
        4'b0001: begin ALU_Result = A_Result; if (A_Result - operand == 0) notZ=0; else notZ = 1;end
        4'b?010: begin ALU_Result = operand; notC = 1; notZ = 1; end
        4'b1011: begin ALU_Result = A_Result + operand; if (A_Result+operand > 15) notC=0; else if (ALU_Result == 0) notZ = 0; else begin notC = 1; notZ = 1; end end
        4'b?100: begin ALU_Result = ~(A_Result | operand); if (ALU_Result == 0) notZ=0; else notZ = 1; end
      endcase
    end

endmodule

uROM.sv
//-----------------------------------------------------------------------------------------------
//     Author: Edgar Alejandro Recancoj Pajarez
//     Proyect: Nibbler
//     Module: uRom
//     Date: 8/11/2018
//     Description of file: uRom for Nibbler
//----------------------------------------------------------------------------------------------

module uROM(
  		input logic [3:0] instruction,
  		input logic clk,
  		input logic phaseOut,
  		input logic [1:0] flagsOut,
  		output logic incPC,
  		output logic notLoadPC,
      output logic notLoadA,
      output logic notLoadFlags,
      output logic notCarryIn,
      output logic [2:0] S,
      output logic notCsRAM,
      output logic notWeRAM,
      output logic notOeALU,
      output logic notOeIN,
      output logic notOeOprnd,
      output logic notLoadOut
		);

    logic [6:0] instr;
    assign instr = {instruction [3:0] , flagsOut [1:0] , phaseOut};

  always @ (instr)
    begin
      casez (instr)
      7'b????_??0:    //any
        begin
          incPC = 1;
          notLoadPC = 1;
          notLoadA = 1;
          notLoadFlags = 1;
          notCarryIn = 1;
          S = 3'b000;
          notCsRAM = 1;
          notWeRAM = 1;
          notOeALU = 0;
          notOeIN = 1;
          notOeOprnd = 1;
          notLoadOut = 1;
        end

      7'b0000_0?1:   //JC
        begin
          incPC = 0;
          notLoadPC = 0;
          notLoadA = 1;
          notLoadFlags = 1;
          notCarryIn = 1;
          S = 3'b000;
          notCsRAM = 1;
          notWeRAM = 1;
          notOeALU = 0;
          notOeIN = 1;
          notOeOprnd = 1;
          notLoadOut = 1;
        end

      7'b0000_1?1:   //JC
        begin
          incPC = 1;
          notLoadPC = 1;
          notLoadA = 1;
          notLoadFlags = 1;
          notCarryIn = 1;
          S = 3'b000;
          notCsRAM = 1;
          notWeRAM = 1;
          notOeALU = 0;
          notOeIN = 1;
          notOeOprnd = 1;
          notLoadOut = 1;
        end

      7'b0001_0?1:   //JNC
        begin
          incPC = 1;
          notLoadPC = 1;
          notLoadA = 1;
          notLoadFlags = 1;
          notCarryIn = 1;
          S = 3'b000;
          notCsRAM = 1;
          notWeRAM = 1;
          notOeALU = 0;
          notOeIN = 1;
          notOeOprnd = 1;
          notLoadOut = 1;
        end

      7'b0001_1?1:   //JNC
        begin
          incPC = 0;
          notLoadPC = 0;
          notLoadA = 1;
          notLoadFlags = 1;
          notCarryIn = 1;
          S = 3'b000;
          notCsRAM = 1;
          notWeRAM = 1;
          notOeALU = 0;
          notOeIN = 1;
          notOeOprnd = 1;
          notLoadOut = 1;
        end

      7'b0010_??1:   //CMPI
        begin
          incPC = 0;
          notLoadPC = 1;
          notLoadA = 1;
          notLoadFlags = 0;
          notCarryIn = 0;
          S = 3'b001;
          notCsRAM = 1;
          notWeRAM = 1;
          notOeALU = 1;
          notOeIN = 1;
          notOeOprnd = 0;
          notLoadOut = 1;
        end

      7'b0010_??1:   //CMPI
        begin
          incPC = 0;
          notLoadPC = 1;
          notLoadA = 1;
          notLoadFlags = 0;
          notCarryIn = 0;
          S = 3'b001;
          notCsRAM = 1;
          notWeRAM = 1;
          notOeALU = 1;
          notOeIN = 1;
          notOeOprnd = 0;
          notLoadOut = 1;
        end

      7'b0011_??1:   //CMPM
        begin
          incPC = 1;
          notLoadPC = 1;
          notLoadA = 1;
          notLoadFlags = 0;
          notCarryIn = 0;
          S = 3'b001;
          notCsRAM = 0;
          notWeRAM = 1;
          notOeALU = 1;
          notOeIN = 1;
          notOeOprnd = 1;
          notLoadOut = 1;
        end

      7'b0100_??1:   //LIT
        begin
          incPC = 0;
          notLoadPC = 1;
          notLoadA = 0;
          notLoadFlags = 0;
          notCarryIn = 0;
          S = 3'b010;
          notCsRAM = 1;
          notWeRAM = 1;
          notOeALU = 1;
          notOeIN = 1;
          notOeOprnd = 0;
          notLoadOut = 1;
        end

      7'b0101_??1:   //IN
        begin
          incPC = 0;
          notLoadPC = 1;
          notLoadA = 0;
          notLoadFlags = 0;
          notCarryIn = 0;
          S = 3'b010;
          notCsRAM = 1;
          notWeRAM = 1;
          notOeALU = 1;
          notOeIN = 0;
          notOeOprnd = 1;
          notLoadOut = 1;
        end

      7'b0110_??1:   //LD
        begin
          incPC = 1;
          notLoadPC = 1;
          notLoadA = 0;
          notLoadFlags = 0;
          notCarryIn = 0;
          S = 3'b010;
          notCsRAM = 0;
          notWeRAM = 1;
          notOeALU = 1;
          notOeIN = 1;
          notOeOprnd = 1;
          notLoadOut = 1;
        end

      7'b0111_??1:   //ST
        begin
          incPC = 1;
          notLoadPC = 1;
          notLoadA = 1;
          notLoadFlags = 1;
          notCarryIn = 1;
          S = 3'b000;
          notCsRAM = 0;
          notWeRAM = 0;
          notOeALU = 0;
          notOeIN = 1;
          notOeOprnd = 1;
          notLoadOut = 1;
        end

      7'b1000_?01:   //JZ
        begin
          incPC = 0;
          notLoadPC = 0;
          notLoadA = 1;
          notLoadFlags = 1;
          notCarryIn = 1;
          S = 3'b000;
          notCsRAM = 1;
          notWeRAM = 1;
          notOeALU = 0;
          notOeIN = 1;
          notOeOprnd = 1;
          notLoadOut = 1;
        end

      7'b1000_?11:   //JZ
        begin
          incPC = 1;
          notLoadPC = 1;
          notLoadA = 1;
          notLoadFlags = 1;
          notCarryIn = 1;
          S = 3'b000;
          notCsRAM = 1;
          notWeRAM = 1;
          notOeALU = 0;
          notOeIN = 1;
          notOeOprnd = 1;
          notLoadOut = 1;
        end

      7'b1001_?01:   //JNZ
        begin
          incPC = 1;
          notLoadPC = 1;
          notLoadA = 1;
          notLoadFlags = 1;
          notCarryIn = 1;
          S = 3'b000;
          notCsRAM = 1;
          notWeRAM = 1;
          notOeALU = 0;
          notOeIN = 1;
          notOeOprnd = 1;
          notLoadOut = 1;
        end

      7'b1001_?11:   //JNZ
        begin
          incPC = 0;
          notLoadPC = 0;
          notLoadA = 1;
          notLoadFlags = 1;
          notCarryIn = 1;
          S = 3'b000;
          notCsRAM = 1;
          notWeRAM = 1;
          notOeALU = 0;
          notOeIN = 1;
          notOeOprnd = 1;
          notLoadOut = 1;
        end

      7'b1010_??1:   //ADDI
        begin
          incPC = 0;
          notLoadPC = 1;
          notLoadA = 0;
          notLoadFlags = 0;
          notCarryIn = 1;
          S = 3'b011;
          notCsRAM = 1;
          notWeRAM = 1;
          notOeALU = 1;
          notOeIN = 1;
          notOeOprnd = 0;
          notLoadOut = 1;
        end

      7'b1011_??1:   //ADDM
        begin
          incPC = 1;
          notLoadPC = 1;
          notLoadA = 0;
          notLoadFlags = 0;
          notCarryIn = 1;
          S = 3'b011;
          notCsRAM = 0;
          notWeRAM = 1;
          notOeALU = 1;
          notOeIN = 1;
          notOeOprnd = 1;
          notLoadOut = 1;
        end

      7'b1100_??1:   //JMP
        begin
          incPC = 0;
          notLoadPC = 0;
          notLoadA = 1;
          notLoadFlags = 1;
          notCarryIn = 1;
          S = 3'b000;
          notCsRAM = 1;
          notWeRAM = 1;
          notOeALU = 0;
          notOeIN = 1;
          notOeOprnd = 1;
          notLoadOut = 1;
        end

      7'b1101_??1:   //OUT
        begin
          incPC = 0;
          notLoadPC = 1;
          notLoadA = 1;
          notLoadFlags = 1;
          notCarryIn = 1;
          S = 3'b000;
          notCsRAM = 1;
          notWeRAM = 1;
          notOeALU = 0;
          notOeIN = 1;
          notOeOprnd = 1;
          notLoadOut = 0;
        end

      7'b1110_??1:   //NORI
        begin
          incPC = 0;
          notLoadPC = 1;
          notLoadA = 0;
          notLoadFlags = 0;
          notCarryIn = 0;
          S = 3'b100;
          notCsRAM = 1;
          notWeRAM = 1;
          notOeALU = 1;
          notOeIN = 1;
          notOeOprnd = 0;
          notLoadOut = 1;
        end

      7'b1111_??1:   //NORM
        begin
          incPC = 1;
          notLoadPC = 1;
          notLoadA = 0;
          notLoadFlags = 0;
          notCarryIn = 0;
          S = 3'b100;
          notCsRAM = 0;
          notWeRAM = 1;
          notOeALU = 1;
          notOeIN = 1;
          notOeOprnd = 1;
          notLoadOut = 1;
        end
      endcase
  end


endmodule

PHASE.sv
//-----------------------------------------------------------------------------------------------
//     Author: Edgar Alejandro Recancoj Pajarez
//     Proyect: Nibbler
//     Module: Phase
//     Date: 8/11/2018
//     Description of file: Phase for Nibbler
//----------------------------------------------------------------------------------------------

module PHASE (input logic clk,
              input logic reset,
              output logic phaseOut
              );



  always @ (posedge clk or posedge reset)
    begin//si esta en reset, se pone q en 0, si no, en el flanco positivo de clk se pasa d a q.
      if (reset)
        phaseOut <= 1'b0;
  	  else
        phaseOut <= ~phaseOut;
    end


endmodule

FLAGS.sv
//-----------------------------------------------------------------------------------------------
//     Author: Edgar Alejandro Recancoj Pajarez
//     Proyect: Nibbler
//     Module: Flags
//     Date: 8/11/2018
//     Description of file: Flags for Nibbler
//----------------------------------------------------------------------------------------------

module FLAGS(input logic notC,
  			     input logic notZ,
  			     input logic reset,
  			     input logic clk,
             input logic notLoadFlags,
  			     output logic [1:0] flagsOut
			       );

  always @ (posedge clk, posedge reset)

    begin

      if(reset)
        flagsOut <= 2'b0;
      else if (notLoadFlags)
        flagsOut <= {notC,notZ};
      else
        flagsOut <= flagsOut;

    end

endmodule

FETCH.sv
//-----------------------------------------------------------------------------------------------
//     Author: Edgar Alejandro Recancoj Pajarez
//     Proyect: Nibbler
//     Module: Fetch
//     Date: 8/11/2018
//     Description of file: Fetch for Nibbler
//-----------------------------------------------------------------------------------------------

module FETCH(
  		input logic [7:0] programByte,
  		input logic clk,
  		input logic phaseOut,
  		input logic reset,
  		output logic [3:0] instruction,
  		output logic [3:0] operand
		);

  always @ (posedge clk , posedge reset)
    begin
    	if(reset)
        {instruction, operand}<= 8'b0;
	      else if (~phaseOut)
        {instruction, operand} <= programByte;
		    else
        {instruction, operand} <= {instruction, operand};


end

endmodule

PROG_ROM.sv
//-----------------------------------------------------------------------------------------------
//     Author: Edgar Alejandro Recancoj Pajarez
//     Proyect: Nibbler
//     Module: Program Memory
//     Date: 8/11/2018
//     Description of file: Program memory for Nibbler
//-----------------------------------------------------------------------------------------------

module PROG_ROM (
        input [11: 0] address , // Address input
        output [7:0] programByte     // Data output
        );


  logic [11:0] mem [0:4095] ;

  assign programByte = mem[address];

initial begin
  $readmemb("PROG_ROM_INSTRUCTIONS.txt", mem); // memory_list is memory file
end

endmodule

PC.sv
//-----------------------------------------------------------------------------------------------
//     Author: Edgar Alejandro Recancoj Pajarez
//     Proyect: Nibbler
//     Module: Program Counter
//     Date: 8/11/2018
//     Description of file: Program counter for Nibbler
//-----------------------------------------------------------------------------------------------

module PC #(parameter N = 12)
        (input logic clk, // clock signal
   			input logic reset,  // reset
        input logic notLoadPC,  //signal control for loading a value to program counter
        input logic incPC,
        input logic [N-1:0] loadAddress,  // address to be loaded if /loadPC is 0
   			output logic [N-1:0] address);  // address for Program Memory

  always @ (posedge clk)
    begin
      if(~notLoadPC)
        address <= loadAddress;
      else if (incPC)
        address <= address + 1;
      else
        address <= address;
    end

  always @ (posedge reset)    // Asynchronous reset
      address <= 0;

endmodule

NIBBLER.sv
//-----------------------------------------------------------------------------------------------
//     Author: Edgar Alejandro Recancoj Pajarez
//     Proyect: Nibbler
//     Module: Nibbler
//     Date: 8/11/2018
//     Description of file: Nibbler funcional
//--------------------------------------------------------------------------------------------

`include "PC.sv"
`include "PROG_ROM.sv"
`include "FETCH.sv"
`include "FLAGS.sv"
`include "PHASE.sv"
`include "uROM.sv"
`include "ALU.sv"
`include "A.sv"

module NIBBLER (input logic clk,
                input logic reset,
                output logic [3:0] salida_acumulador,
                output logic reloj,
                output logic fase,
                output logic [7:0] prog,
                output logic [11:0] direccion,
                output logic notCarry,
                output logic notZero
                );

  wire [11:0] address, loadAddress;
  wire [7:0] programByte;
  wire [3:0] instruction, operand, ALU_Result, A_Result;
  wire [2:0] S;
  wire [1:0] flagsOut;
  wire incPC, notLoadPC,notLoadA,notLoadFlags,notCarryIn, notCsRAM, phaseOut;
  wire notWeRAM, notOeALU, notOeIN, notOeOprnd, notLoadOut,  notZ, notC;

  assign loadAddress = 0;



  PC pc (clk, reset, notLoadPC, incPC, loadAddress, address);

  PROG_ROM prog_rom (address, programByte);

  FETCH fetch (programByte, clk, phaseOut, reset, instruction, operand);

  FLAGS flags (notC, notZ, reset, clk, notLoadFlags, flagsOut);

  PHASE phase1 (clk, reset, phaseOut);

  uROM micro_rom (instruction, clk, phaseOut, flagsOut, incPC, notLoadPC, notLoadA,
                  notLoadFlags, notCarryIn, S, notCsRAM, notWeRAM, notOeALU, notOeIN,
                  notOeOprnd, notLoadOut);

  ALU alu (notCarryIn, S, A_Result, operand, notOeALU, notC, notZ, ALU_Result);

  A acumulador(clk, reset, ALU_Result, A_Result);

  assign salida_acumulador = ALU_Result;
  assign reloj = clk;
  assign fase = phaseOut;
  assign direccion = address;
  assign prog = programByte;
  assign notCarry = notC;
  assign notZero = notZ;




endmodule // NIBBLER

NIBBLER_Testbench.sv
//-----------------------------------------------------------------------------------------------
//     Author: Edgar Alejandro Recancoj Pajarez
//     Proyect: Nibbler
//     Module: Nibbler Testbench
//     Date: 8/11/2018
//     Description of file: Nibbler funcional Testbench
//--------------------------------------------------------------------------------------------

//OJO: ESTE ES EL CODIGO QUE SE DEBE DE COMPILAR. EL RESULTADO EN CONSOLA VA A HACER
//EL RESULTADO DE LAS SIGUIENTES OPERACIONES (QUE ESTAN EN LA PROG MEMORY)
//0100_0000	// LIT 0
//0100_0100	// LIT 1
//0100_0000	// LIT 0
//0100_1111	// LIT 15
//1110_1111	// NORI 15
//1010_0001	// ADDI 1
//0010_0001	// COMPI 1


`include "NIBBLER.sv"

module nibbler_testbench();
  //Se declaran salidas y entradas
  logic clk, reset, fase,  notCarry, notZero;
  logic [3:0] salida_acumulador;
  logic [7:0] prog;
  logic [11:0] direccion;

  NIBBLER dut (clk, reset, salida_acumulador, reloj, fase, prog ,direccion, notCarry, notZero);

  initial
    begin
      //Se configura el display y monitor para observar tiempo, reset, clk, j, k y q
      $display("Tiempo\t\t\tsalida_acumulador \treloj \t\tfase \tnotCarry \tnotZero \t\tdireccion \t\tprog");
      $monitor("%d \t%b \t\t\t%b \t\t%b \t%b \t\t%b \t\t%b \t\t%b", $time, salida_acumulador, reloj, fase , notCarry, notZero, direccion, prog);
      //Se inicializan variables
      reset = 0;
      clk = 0;

      #1 reset = 1;
      #1 reset = 0;


    end


  initial
    begin
      #20 $finish;
    end

  // señal de reloj
  always
    #5 clk = ~clk;

endmodule

dump.vcd
$date
	Sun Nov 11 15:10:14 2018
$end
$version
	Icarus Verilog
$end
$timescale
	1s
$end
$scope module nibbler_testbench $end
$var wire 4 ! salida_acumulador [3:0] $end
$var wire 1 " reloj $end
$var wire 8 # prog [7:0] $end
$var wire 1 $ notZero $end
$var wire 1 % notCarry $end
$var wire 1 & fase $end
$var wire 12 ' direccion [11:0] $end
$var reg 1 ( clk $end
$var reg 1 ) reset $end
$upscope $end
$enddefinitions $end
#0
$dumpvars
0)
0(
bx '
x&
x%
x$
bx #
0"
bx !
$end
#1
1$
1%
b0 !
b10100001 #
0&
b0 '
1)
#2
0)
#5
b1 !
bx #
1&
b1 '
1"
1(
#10
0"
0(
#15
0&
1"
1(
#20
0"
0(
#25
1&
b10 '
1"
1(
#30
0"
0(
#35
0&
b11 '
1"
1(
#40
0"
0(
#45
1&
b100 '
1"
1(
#50
0"
0(
#55
0&
b101 '
1"
1(
#60
0"
0(
#65
1&
b110 '
1"
1(
#70
0"
0(
#75
0&
b111 '
1"
1(
#80
0"
0(
#85
1&
b1000 '
1"
1(
#90
0"
0(
#95
0&
b1001 '
1"
1(
#100
0"
0(
#105
1&
b1010 '
1"
1(
#110
0"
0(
#115
0&
b1011 '
1"
1(
#120
0"
0(
#125
1&
b1100 '
1"
1(
#130
0"
0(
#135
0&
b1101 '
1"
1(
#140
0"
0(
#145
1&
b1110 '
1"
1(
#150
0"
0(
#155
0&
b1111 '
1"
1(
#160
0"
0(
#165
1&
b10000 '
1"
1(
#170
0"
0(
#175
0&
b10001 '
1"
1(
#180
0"
0(
#185
1&
b10010 '
1"
1(
#190
0"
0(
#195
0&
b10011 '
1"
1(
#200
0"
0(
#205
1&
b10100 '
1"
1(
#210
0"
0(
#215
0&
b10101 '
1"
1(
#220
0"
0(
#225
1&
b10110 '
1"
1(
#230
0"
0(
#235
0&
b10111 '
1"
1(
#240
0"
0(
#245
1&
b11000 '
1"
1(
#250
0"
0(
#255
0&
b11001 '
1"
1(
#260
0"
0(
#265
1&
b11010 '
1"
1(
#270
0"
0(
#275
0&
b11011 '
1"
1(
#280
0"
0(
#285
1&
b11100 '
1"
1(
#290
0"
0(
#295
0&
b11101 '
1"
1(
#300
0"
0(
#305
1&
b11110 '
1"
1(
#310
0"
0(
#315
0&
b11111 '
1"
1(
#320
0"
0(
#325
1&
b100000 '
1"
1(
#330
0"
0(
#335
0&
b100001 '
1"
1(
#340
0"
0(
#345
1&
b100010 '
1"
1(
#350
0"
0(
#355
0&
b100011 '
1"
1(
#360
0"
0(
#365
1&
b100100 '
1"
1(
#370
0"
0(
#375
0&
b100101 '
1"
1(
#380
0"
0(
#385
1&
b100110 '
1"
1(
#390
0"
0(
#395
0&
b100111 '
1"
1(
#400
0"
0(
